ml2/__init__.py
ml2_1416-0.1.0.dist-info/METADATA
ml2_1416-0.1.0.dist-info/WHEEL
ml2_1416-0.1.0.dist-info/top_level.txt
ml2_1416-0.1.0.dist-info/RECORD
