Metadata-Version: 2.4
Name: ml2_1416
Version: 0.1.0
Summary: A simple greeting module called ML2
Author-email: Your Name <your@email.com>
License: MIT
Requires-Python: >=3.6
